{
  "version": "1.20.4",
  "description": "Kubernetes kubectl CLI",
  "homepage": "https://kubernetes.io/",
  "license": "Apache-2.0",
  "architecture": {
    "64bit": {
      "url": "https://dl.k8s.io/release/v1.20.4/bin/windows/amd64/kubectl.exe",
      "hash": "7139c8e4873347d15ec72fe61ef1a2025d37f2e47797d9e1b0d0f8f1a8ae5939"
    },
    "32bit": {
      "url": "https://dl.k8s.io/release/v1.20.4/bin/windows/386/kubectl.exe",
      "hash": "58f0869c8db4d6f3d32d7454d0c63d64a6ee0307c22c30778ddececf70b548a7"
    }
  },
  "bin": [
    "kubectl.exe"
  ]
}