{
  "version": "1.25.6",
  "description": "Kubernetes kubectl CLI",
  "homepage": "https://kubernetes.io/",
  "license": "Apache-2.0",
  "architecture": {
    "64bit": {
      "url": "https://dl.k8s.io/release/v1.25.6/bin/windows/amd64/kubectl.exe",
      "hash": "6031ee04eba4e0d39cd8598829e3acaf2473938f97287703bd264114580ad1cb"
    },
    "arm64": {
      "url": "https://dl.k8s.io/release/v1.25.6/bin/windows/arm64/kubectl.exe",
      "hash": "f4b7e02047939ea867fe20b00f02d88e780195ca46a2c7fc31ef6ca869f0affe"
    },
    "32bit": {
      "url": "https://dl.k8s.io/release/v1.25.6/bin/windows/386/kubectl.exe",
      "hash": "54381b5768480b1d9c8292d26f0674b91c7ad2089a954a2ce582c6296af36e43"
    }
  },
  "bin": [
    "kubectl.exe"
  ]
}